npf_renderer/__init__.py
npf_renderer/exceptions.py
npf_renderer/format_npf.py
npf_renderer/helpers.py
npf_renderer/utils.py
npf_renderer/format/__init__.py
npf_renderer/format/attribution.py
npf_renderer/format/base.py
npf_renderer/format/i18n.py
npf_renderer/format/image.py
npf_renderer/format/inline.py
npf_renderer/format/misc.py
npf_renderer/format/text.py
npf_renderer/objects/__init__.py
npf_renderer/objects/attribution.py
npf_renderer/objects/audio_block.py
npf_renderer/objects/embed_iframe.py
npf_renderer/objects/image.py
npf_renderer/objects/inline.py
npf_renderer/objects/layouts.py
npf_renderer/objects/link_block.py
npf_renderer/objects/media_objects.py
npf_renderer/objects/poll_block.py
npf_renderer/objects/text_block.py
npf_renderer/objects/unsupported.py
npf_renderer/objects/video_block.py
npf_renderer/parse/__init__.py
npf_renderer/parse/base.py
npf_renderer/parse/layout_parse.py
npf_renderer/parse/misc.py
npf_renderer/parse/parse.py
npf_renderer-0.13.0.dist-info/LICENSE
npf_renderer-0.13.0.dist-info/METADATA
npf_renderer-0.13.0.dist-info/WHEEL
npf_renderer-0.13.0.dist-info/top_level.txt
npf_renderer-0.13.0.dist-info/RECORD
