Metadata-Version: 2.2
Name: npf_renderer
Version: 0.13.0
Summary: A Python Based Renderer for Tumblr's Neue Post Format (NPF) 
Project-URL: Homepage, https://github.com/syeopite/npf-renderer
Project-URL: Source, https://github.com/syeopite/npf-renderer
Classifier: Development Status :: 4 - Beta
Classifier: Programming Language :: Python :: 3.10
Classifier: Programming Language :: Python :: 3.11
Classifier: Programming Language :: Python :: 3.12
Classifier: License :: OSI Approved :: MIT License
Classifier: Operating System :: OS Independent
Classifier: Topic :: Internet :: WWW/HTTP :: Dynamic Content
Classifier: Topic :: Multimedia
Classifier: Topic :: Software Development :: Libraries :: Python Modules
Requires-Python: >=3.10
License-File: LICENSE
Requires-Dist: dominate>=2.8.0
Requires-Dist: intervaltree>=3.1.0
Provides-Extra: dev
Requires-Dist: pytest==8.3.4; extra == "dev"
Requires-Dist: prettyprinter==0.18.0; extra == "dev"
Requires-Dist: freezegun==1.5.1; extra == "dev"
Requires-Dist: black==25.1.0; extra == "dev"
